gusense/__init__.py
gusense/api/__init__.py
gusense/api/client.py
gusense/api/data_api.py
gusense/common/__init__.py
gusense/common/constant.py
gusense/common/credit.py
gusense/util/__init__.py
gusense/util/common.py
gusense-1.1.8.dist-info/LICENSE
gusense-1.1.8.dist-info/METADATA
gusense-1.1.8.dist-info/WHEEL
gusense-1.1.8.dist-info/top_level.txt
gusense-1.1.8.dist-info/RECORD
