Metadata-Version: 2.1
Name: gusense
Version: 1.1.8
Summary: This is API util
Home-page: https://www.python.org
Author: wgp
Author-email: 284250692@qq.com
License: BSD License
Platform: UNKNOWN
Classifier: License :: OSI Approved :: BSD License
Classifier: Intended Audience :: Developers
Classifier: Operating System :: OS Independent
Classifier: Programming Language :: Python
Classifier: Programming Language :: Python :: 2.7
Classifier: Programming Language :: Python :: 3
Classifier: Programming Language :: Python :: 3.3
Classifier: Programming Language :: Python :: 3.4
Classifier: Programming Language :: Python :: 3.5
Requires-Python: >=2.7
License-File: LICENSE
Requires-Dist: requests
Requires-Dist: pandas
